{
  "competitionName": "Klasa B (Stalowa Wola II)",
  "count": 105,
  "matches": [
    {
      "competition": {
        "name": "Klasa B (Stalowa Wola II)"
      },
      "homeTeam": {
        "name": "Herosi Krzaki-Słomiana",
        "crest": null
      },
      "awayTeam": {
        "name": "Orzeł Rudnik nad Sanem",
        "crest": null
      },
      "date": {
        "date": "2026-03-28",
        "dateTime": "2026-03-28T16:00:00.000Z"
      },
      "id": "4a24c540e0406a588612819c421ac313"
    },
    {
      "competition": {
        "name": "Klasa B (Stalowa Wola II)"
      },
      "homeTeam": {
        "name": "Rotunda Krzeszów",
        "crest": null
      },
      "awayTeam": {
        "name": "Czarni II Lipa",
        "crest": null
      },
      "date": {
        "date": "2026-03-29",
        "dateTime": "2026-03-29T11:00:00.000Z"
      },
      "id": "194ee7cd2b97a51e134cd2cb4d92e6c0"
    },
    {
      "competition": {
        "name": "Klasa B (Stalowa Wola II)"
      },
      "homeTeam": {
        "name": "LZS Turbia",
        "crest": null
      },
      "awayTeam": {
        "name": "Ceramika Harasiuki",
        "crest": null
      },
      "date": {
        "date": "2026-03-29",
        "dateTime": "2026-03-29T11:00:00.000Z"
      },
      "id": "826d47506fc855bdec032d27a7582135"
    },
    {
      "competition": {
        "name": "Klasa B (Stalowa Wola II)"
      },
      "homeTeam": {
        "name": "LZS Rzeczyca Długa",
        "crest": null
      },
      "awayTeam": {
        "name": "Sanna Zaklików",
        "crest": null
      },
      "date": {
        "date": "2026-03-29",
        "dateTime": "2026-03-29T11:00:00.000Z"
      },
      "id": "12237dff5e13d4a88ec06ec2b8bf1d87"
    },
    {
      "competition": {
        "name": "Klasa B (Stalowa Wola II)"
      },
      "homeTeam": {
        "name": "Huragan Zdziechowice",
        "crest": null
      },
      "awayTeam": {
        "name": "WKS Kurzyna",
        "crest": null
      },
      "date": {
        "date": "2026-03-29",
        "dateTime": "2026-03-29T12:30:00.000Z"
      },
      "id": "aba54c7c051ded83b82c4036b2bd98bd"
    },
    {
      "competition": {
        "name": "Klasa B (Stalowa Wola II)"
      },
      "homeTeam": {
        "name": "San Rozwadów (Stalowa Wola)",
        "crest": null
      },
      "awayTeam": {
        "name": "LZS Przędzel",
        "crest": null
      },
      "date": {
        "date": "2026-03-29",
        "dateTime": "2026-03-29T13:00:00.000Z"
      },
      "id": "60790c51bac9ec080598d630c63ba51b"
    },
    {
      "competition": {
        "name": "Klasa B (Stalowa Wola II)"
      },
      "homeTeam": {
        "name": "Jutrzenka Kopki",
        "crest": null
      },
      "awayTeam": {
        "name": "Orzeł Glinianka",
        "crest": null
      },
      "date": {
        "date": "2026-03-29",
        "dateTime": "2026-03-29T14:00:00.000Z"
      },
      "id": "5945b7b485d91ee3d63a7ebe70a06341"
    },
    {
      "competition": {
        "name": "Klasa B (Stalowa Wola II)"
      },
      "homeTeam": {
        "name": "Orzeł Glinianka",
        "crest": null
      },
      "awayTeam": {
        "name": "LZS Rzeczyca Długa",
        "crest": null
      },
      "date": {
        "date": "2026-04-04",
        "dateTime": "2026-04-04T11:00:00.000Z"
      },
      "id": "cba2ed336ebba061a80149951d478fc5"
    },
    {
      "competition": {
        "name": "Klasa B (Stalowa Wola II)"
      },
      "homeTeam": {
        "name": "WKS Kurzyna",
        "crest": null
      },
      "awayTeam": {
        "name": "Herosi Krzaki-Słomiana",
        "crest": null
      },
      "date": {
        "date": "2026-04-04",
        "dateTime": "2026-04-04T11:00:00.000Z"
      },
      "id": "3e74274bec7e504f8cdbd3ee053e63bf"
    },
    {
      "competition": {
        "name": "Klasa B (Stalowa Wola II)"
      },
      "homeTeam": {
        "name": "Ceramika Harasiuki",
        "crest": null
      },
      "awayTeam": {
        "name": "Rotunda Krzeszów",
        "crest": null
      },
      "date": {
        "date": "2026-04-04",
        "dateTime": "2026-04-04T11:00:00.000Z"
      },
      "id": "96f98752a56163b40efb9a3935b262b3"
    },
    {
      "competition": {
        "name": "Klasa B (Stalowa Wola II)"
      },
      "homeTeam": {
        "name": "Sanna Zaklików",
        "crest": null
      },
      "awayTeam": {
        "name": "Huragan Zdziechowice",
        "crest": null
      },
      "date": {
        "date": "2026-04-04",
        "dateTime": "2026-04-04T13:00:00.000Z"
      },
      "id": "6e7e3726198a1ce5814c29523eaf8f6c"
    },
    {
      "competition": {
        "name": "Klasa B (Stalowa Wola II)"
      },
      "homeTeam": {
        "name": "Czarni II Lipa",
        "crest": null
      },
      "awayTeam": {
        "name": "San Rozwadów (Stalowa Wola)",
        "crest": null
      },
      "date": {
        "date": "2026-04-04",
        "dateTime": "2026-04-04T14:00:00.000Z"
      },
      "id": "e240bc1a86cf84418745fe330539d63f"
    },
    {
      "competition": {
        "name": "Klasa B (Stalowa Wola II)"
      },
      "homeTeam": {
        "name": "LZS Przędzel",
        "crest": null
      },
      "awayTeam": {
        "name": "Jutrzenka Kopki",
        "crest": null
      },
      "date": {
        "date": "2026-04-04",
        "dateTime": "2026-04-04T14:00:00.000Z"
      },
      "id": "cf5c2be379f5183bd722239d04af4538"
    },
    {
      "competition": {
        "name": "Klasa B (Stalowa Wola II)"
      },
      "homeTeam": {
        "name": "Orzeł Rudnik nad Sanem",
        "crest": null
      },
      "awayTeam": {
        "name": "LZS Turbia",
        "crest": null
      },
      "date": {
        "date": "2026-04-04",
        "dateTime": "2026-04-04T14:00:00.000Z"
      },
      "id": "ecc154c9d6768361f01331fe4f500c18"
    },
    {
      "competition": {
        "name": "Klasa B (Stalowa Wola II)"
      },
      "homeTeam": {
        "name": "Herosi Krzaki-Słomiana",
        "crest": null
      },
      "awayTeam": {
        "name": "Ceramika Harasiuki",
        "crest": null
      },
      "date": {
        "date": "2026-08-10",
        "dateTime": "2026-08-10T12:00:00.000Z"
      },
      "id": "58f3db3bae41d9ae97f2d86e50a56556"
    },
    {
      "competition": {
        "name": "Klasa B (Stalowa Wola II)"
      },
      "homeTeam": {
        "name": "LZS Przędzel",
        "crest": null
      },
      "awayTeam": {
        "name": "Czarni II Lipa",
        "crest": null
      },
      "date": {
        "date": "2026-08-10",
        "dateTime": "2026-08-10T14:00:00.000Z"
      },
      "id": "4c1db9ded4a9a88fda7ba25511c77f6f"
    },
    {
      "competition": {
        "name": "Klasa B (Stalowa Wola II)"
      },
      "homeTeam": {
        "name": "San Rozwadów (Stalowa Wola)",
        "crest": null
      },
      "awayTeam": {
        "name": "Orzeł Glinianka",
        "crest": null
      },
      "date": {
        "date": "2026-08-10",
        "dateTime": "2026-08-10T14:00:00.000Z"
      },
      "id": "d91c959f8db1d15e710d871bb1fb0ec0"
    },
    {
      "competition": {
        "name": "Klasa B (Stalowa Wola II)"
      },
      "homeTeam": {
        "name": "LZS Rzeczyca Długa",
        "crest": null
      },
      "awayTeam": {
        "name": "WKS Kurzyna",
        "crest": null
      },
      "date": {
        "date": "2026-08-10",
        "dateTime": "2026-08-10T14:00:00.000Z"
      },
      "id": "ce4a547d739a690e2ebd5c289f32b5e1"
    },
    {
      "competition": {
        "name": "Klasa B (Stalowa Wola II)"
      },
      "homeTeam": {
        "name": "Huragan Zdziechowice",
        "crest": null
      },
      "awayTeam": {
        "name": "Orzeł Rudnik nad Sanem",
        "crest": null
      },
      "date": {
        "date": "2026-08-10",
        "dateTime": "2026-08-10T16:00:00.000Z"
      },
      "id": "a496ea05cacf252eff84af5c7ca6c175"
    },
    {
      "competition": {
        "name": "Klasa B (Stalowa Wola II)"
      },
      "homeTeam": {
        "name": "Jutrzenka Kopki",
        "crest": null
      },
      "awayTeam": {
        "name": "Sanna Zaklików",
        "crest": null
      },
      "date": {
        "date": "2026-08-10",
        "dateTime": "2026-08-10T17:00:00.000Z"
      },
      "id": "fd71d935f9ec6a71c37591cd81eac4fe"
    },
    {
      "competition": {
        "name": "Klasa B (Stalowa Wola II)"
      },
      "homeTeam": {
        "name": "LZS Turbia",
        "crest": null
      },
      "awayTeam": {
        "name": "Rotunda Krzeszów",
        "crest": null
      },
      "date": {
        "date": "2026-08-10",
        "dateTime": "2026-08-10T17:00:00.000Z"
      },
      "id": "8aec88f8e711ad7474cfd9183ecbad4a"
    },
    {
      "competition": {
        "name": "Klasa B (Stalowa Wola II)"
      },
      "homeTeam": {
        "name": "Czarni II Lipa",
        "crest": null
      },
      "awayTeam": {
        "name": "Rotunda Krzeszów",
        "crest": null
      },
      "date": {
        "date": "2026-08-16",
        "dateTime": "2026-08-16T16:00:00.000Z"
      },
      "id": "e036d04705a70395001ee54eec0d8274"
    },
    {
      "competition": {
        "name": "Klasa B (Stalowa Wola II)"
      },
      "homeTeam": {
        "name": "Orzeł Rudnik nad Sanem",
        "crest": null
      },
      "awayTeam": {
        "name": "Herosi Krzaki-Słomiana",
        "crest": null
      },
      "date": {
        "date": "2026-08-16",
        "dateTime": "2026-08-16T17:00:00.000Z"
      },
      "id": "a0669e02ae2613f9401c5788993a870c"
    },
    {
      "competition": {
        "name": "Klasa B (Stalowa Wola II)"
      },
      "homeTeam": {
        "name": "WKS Kurzyna",
        "crest": null
      },
      "awayTeam": {
        "name": "Huragan Zdziechowice",
        "crest": null
      },
      "date": {
        "date": "2026-08-16",
        "dateTime": "2026-08-16T17:30:00.000Z"
      },
      "id": "e99e815465f87e3530eb8df024da9dba"
    },
    {
      "competition": {
        "name": "Klasa B (Stalowa Wola II)"
      },
      "homeTeam": {
        "name": "Ceramika Harasiuki",
        "crest": null
      },
      "awayTeam": {
        "name": "LZS Turbia",
        "crest": null
      },
      "date": {
        "date": "2026-08-17",
        "dateTime": "2026-08-17T11:00:00.000Z"
      },
      "id": "aa7f652388de6e4c9fb7c7976632806f"
    },
    {
      "competition": {
        "name": "Klasa B (Stalowa Wola II)"
      },
      "homeTeam": {
        "name": "LZS Przędzel",
        "crest": null
      },
      "awayTeam": {
        "name": "San Rozwadów (Stalowa Wola)",
        "crest": null
      },
      "date": {
        "date": "2026-08-17",
        "dateTime": "2026-08-17T14:00:00.000Z"
      },
      "id": "6a3dfecc14576a47ebe8767445134f5a"
    },
    {
      "competition": {
        "name": "Klasa B (Stalowa Wola II)"
      },
      "homeTeam": {
        "name": "Sanna Zaklików",
        "crest": null
      },
      "awayTeam": {
        "name": "LZS Rzeczyca Długa",
        "crest": null
      },
      "date": {
        "date": "2026-08-17",
        "dateTime": "2026-08-17T17:00:00.000Z"
      },
      "id": "f56ae22d393370aabc9e38ddac3427ec"
    },
    {
      "competition": {
        "name": "Klasa B (Stalowa Wola II)"
      },
      "homeTeam": {
        "name": "Orzeł Glinianka",
        "crest": null
      },
      "awayTeam": {
        "name": "Jutrzenka Kopki",
        "crest": null
      },
      "date": {
        "date": "2026-08-17",
        "dateTime": "2026-08-17T17:00:00.000Z"
      },
      "id": "dce9e3f04d9298626b8ea3251cc136e9"
    },
    {
      "competition": {
        "name": "Klasa B (Stalowa Wola II)"
      },
      "homeTeam": {
        "name": "Herosi Krzaki-Słomiana",
        "crest": null
      },
      "awayTeam": {
        "name": "WKS Kurzyna",
        "crest": null
      },
      "date": {
        "date": "2026-08-23",
        "dateTime": "2026-08-23T17:00:00.000Z"
      },
      "id": "a7776b52cb2885b7bb6c8811589c25e8"
    },
    {
      "competition": {
        "name": "Klasa B (Stalowa Wola II)"
      },
      "homeTeam": {
        "name": "Rotunda Krzeszów",
        "crest": null
      },
      "awayTeam": {
        "name": "Ceramika Harasiuki",
        "crest": null
      },
      "date": {
        "date": "2026-08-24",
        "dateTime": "2026-08-24T11:00:00.000Z"
      },
      "id": "92c4a8772cfd299f9dfd31a6e1fc3fa3"
    },
    {
      "competition": {
        "name": "Klasa B (Stalowa Wola II)"
      },
      "homeTeam": {
        "name": "San Rozwadów (Stalowa Wola)",
        "crest": null
      },
      "awayTeam": {
        "name": "Czarni II Lipa",
        "crest": null
      },
      "date": {
        "date": "2026-08-24",
        "dateTime": "2026-08-24T14:00:00.000Z"
      },
      "id": "6c70896e6396f08490a05bb9712b5320"
    },
    {
      "competition": {
        "name": "Klasa B (Stalowa Wola II)"
      },
      "homeTeam": {
        "name": "Huragan Zdziechowice",
        "crest": null
      },
      "awayTeam": {
        "name": "Sanna Zaklików",
        "crest": null
      },
      "date": {
        "date": "2026-08-24",
        "dateTime": "2026-08-24T14:00:00.000Z"
      },
      "id": "ef7a90e08976149cbcae37818c06a8be"
    },
    {
      "competition": {
        "name": "Klasa B (Stalowa Wola II)"
      },
      "homeTeam": {
        "name": "Jutrzenka Kopki",
        "crest": null
      },
      "awayTeam": {
        "name": "LZS Przędzel",
        "crest": null
      },
      "date": {
        "date": "2026-08-24",
        "dateTime": "2026-08-24T17:00:00.000Z"
      },
      "id": "a565009f0ce480ad5a425f4f0789f27a"
    },
    {
      "competition": {
        "name": "Klasa B (Stalowa Wola II)"
      },
      "homeTeam": {
        "name": "LZS Rzeczyca Długa",
        "crest": null
      },
      "awayTeam": {
        "name": "Orzeł Glinianka",
        "crest": null
      },
      "date": {
        "date": "2026-08-24",
        "dateTime": "2026-08-24T17:00:00.000Z"
      },
      "id": "b0864db2da169781ad3401928919e010"
    },
    {
      "competition": {
        "name": "Klasa B (Stalowa Wola II)"
      },
      "homeTeam": {
        "name": "LZS Turbia",
        "crest": null
      },
      "awayTeam": {
        "name": "Orzeł Rudnik nad Sanem",
        "crest": null
      },
      "date": {
        "date": "2026-08-24",
        "dateTime": "2026-08-24T17:00:00.000Z"
      },
      "id": "6327b38948a3d902684296a0a2d190c1"
    },
    {
      "competition": {
        "name": "Klasa B (Stalowa Wola II)"
      },
      "homeTeam": {
        "name": "Czarni II Lipa",
        "crest": null
      },
      "awayTeam": {
        "name": "Ceramika Harasiuki",
        "crest": null
      },
      "date": {
        "date": "2026-08-30",
        "dateTime": "2026-08-30T14:00:00.000Z"
      },
      "id": "9320cf647ba00d4dcd6ace37dc5aa411"
    },
    {
      "competition": {
        "name": "Klasa B (Stalowa Wola II)"
      },
      "homeTeam": {
        "name": "WKS Kurzyna",
        "crest": null
      },
      "awayTeam": {
        "name": "LZS Turbia",
        "crest": null
      },
      "date": {
        "date": "2026-08-31",
        "dateTime": "2026-08-31T14:00:00.000Z"
      },
      "id": "124cf526af44f758439f8b355a4a0c2b"
    },
    {
      "competition": {
        "name": "Klasa B (Stalowa Wola II)"
      },
      "homeTeam": {
        "name": "Orzeł Glinianka",
        "crest": null
      },
      "awayTeam": {
        "name": "Huragan Zdziechowice",
        "crest": null
      },
      "date": {
        "date": "2026-08-31",
        "dateTime": "2026-08-31T14:00:00.000Z"
      },
      "id": "4febf8c66869ffdb8a87c06fa2b26b81"
    },
    {
      "competition": {
        "name": "Klasa B (Stalowa Wola II)"
      },
      "homeTeam": {
        "name": "San Rozwadów (Stalowa Wola)",
        "crest": null
      },
      "awayTeam": {
        "name": "Jutrzenka Kopki",
        "crest": null
      },
      "date": {
        "date": "2026-08-31",
        "dateTime": "2026-08-31T14:00:00.000Z"
      },
      "id": "a428a23335457a0875781696473c782a"
    },
    {
      "competition": {
        "name": "Klasa B (Stalowa Wola II)"
      },
      "homeTeam": {
        "name": "Orzeł Rudnik nad Sanem",
        "crest": null
      },
      "awayTeam": {
        "name": "Rotunda Krzeszów",
        "crest": null
      },
      "date": {
        "date": "2026-08-31",
        "dateTime": "2026-08-31T15:00:00.000Z"
      },
      "id": "7655b910488e9c36ea075a1911298430"
    },
    {
      "competition": {
        "name": "Klasa B (Stalowa Wola II)"
      },
      "homeTeam": {
        "name": "Sanna Zaklików",
        "crest": null
      },
      "awayTeam": {
        "name": "Herosi Krzaki-Słomiana",
        "crest": null
      },
      "date": {
        "date": "2026-08-31",
        "dateTime": "2026-08-31T16:00:00.000Z"
      },
      "id": "5dde791b1e0f0a4a8edb7a9ae974ce37"
    },
    {
      "competition": {
        "name": "Klasa B (Stalowa Wola II)"
      },
      "homeTeam": {
        "name": "LZS Przędzel",
        "crest": null
      },
      "awayTeam": {
        "name": "LZS Rzeczyca Długa",
        "crest": null
      },
      "date": {
        "date": "2026-08-31",
        "dateTime": "2026-08-31T17:00:00.000Z"
      },
      "id": "7fbebf9267b1657c8c48e1848e93718f"
    },
    {
      "competition": {
        "name": "Klasa B (Stalowa Wola II)"
      },
      "homeTeam": {
        "name": "Ceramika Harasiuki",
        "crest": null
      },
      "awayTeam": {
        "name": "Orzeł Rudnik nad Sanem",
        "crest": null
      },
      "date": {
        "date": "2026-09-06",
        "dateTime": "2026-09-06T16:30:00.000Z"
      },
      "id": "1063417ec642bb4e6d90957e5ab0484a"
    },
    {
      "competition": {
        "name": "Klasa B (Stalowa Wola II)"
      },
      "homeTeam": {
        "name": "Huragan Zdziechowice",
        "crest": null
      },
      "awayTeam": {
        "name": "LZS Przędzel",
        "crest": null
      },
      "date": {
        "date": "2026-09-07",
        "dateTime": "2026-09-07T13:00:00.000Z"
      },
      "id": "c51586e46157f6a89e4218ba5b9ad16d"
    },
    {
      "competition": {
        "name": "Klasa B (Stalowa Wola II)"
      },
      "homeTeam": {
        "name": "Rotunda Krzeszów",
        "crest": null
      },
      "awayTeam": {
        "name": "WKS Kurzyna",
        "crest": null
      },
      "date": {
        "date": "2026-09-07",
        "dateTime": "2026-09-07T13:00:00.000Z"
      },
      "id": "6c58fbbc30fae27f530b6922a2aad702"
    },
    {
      "competition": {
        "name": "Klasa B (Stalowa Wola II)"
      },
      "homeTeam": {
        "name": "LZS Turbia",
        "crest": null
      },
      "awayTeam": {
        "name": "Sanna Zaklików",
        "crest": null
      },
      "date": {
        "date": "2026-09-07",
        "dateTime": "2026-09-07T15:30:00.000Z"
      },
      "id": "0458379557fe2bdbcc11820affe6512f"
    },
    {
      "competition": {
        "name": "Klasa B (Stalowa Wola II)"
      },
      "homeTeam": {
        "name": "Jutrzenka Kopki",
        "crest": null
      },
      "awayTeam": {
        "name": "Czarni II Lipa",
        "crest": null
      },
      "date": {
        "date": "2026-09-07",
        "dateTime": "2026-09-07T16:00:00.000Z"
      },
      "id": "643f780c4d8ba01a50a4b0cd348edb6d"
    },
    {
      "competition": {
        "name": "Klasa B (Stalowa Wola II)"
      },
      "homeTeam": {
        "name": "LZS Rzeczyca Długa",
        "crest": null
      },
      "awayTeam": {
        "name": "San Rozwadów (Stalowa Wola)",
        "crest": null
      },
      "date": {
        "date": "2026-09-07",
        "dateTime": "2026-09-07T16:00:00.000Z"
      },
      "id": "63da40048eefb1c8909b3f1ed570d727"
    },
    {
      "competition": {
        "name": "Klasa B (Stalowa Wola II)"
      },
      "homeTeam": {
        "name": "Herosi Krzaki-Słomiana",
        "crest": null
      },
      "awayTeam": {
        "name": "Orzeł Glinianka",
        "crest": null
      },
      "date": {
        "date": "2026-09-07",
        "dateTime": "2026-09-07T16:30:00.000Z"
      },
      "id": "99a2592f3c569b9d0cbe7144340235df"
    },
    {
      "competition": {
        "name": "Klasa B (Stalowa Wola II)"
      },
      "homeTeam": {
        "name": "Czarni II Lipa",
        "crest": null
      },
      "awayTeam": {
        "name": "Orzeł Rudnik nad Sanem",
        "crest": null
      },
      "date": {
        "date": "2026-09-13",
        "dateTime": "2026-09-13T16:00:00.000Z"
      },
      "id": "3b07c457f973251ebc12ca157f196a21"
    },
    {
      "competition": {
        "name": "Klasa B (Stalowa Wola II)"
      },
      "homeTeam": {
        "name": "Jutrzenka Kopki",
        "crest": null
      },
      "awayTeam": {
        "name": "LZS Rzeczyca Długa",
        "crest": null
      },
      "date": {
        "date": "2026-09-13",
        "dateTime": "2026-09-13T16:30:00.000Z"
      },
      "id": "f8f553db01b6d63fda617752113920e5"
    },
    {
      "competition": {
        "name": "Klasa B (Stalowa Wola II)"
      },
      "homeTeam": {
        "name": "Sanna Zaklików",
        "crest": null
      },
      "awayTeam": {
        "name": "Rotunda Krzeszów",
        "crest": null
      },
      "date": {
        "date": "2026-09-13",
        "dateTime": "2026-09-13T17:00:00.000Z"
      },
      "id": "cd936e6a9bf50309281031e63d378a8b"
    },
    {
      "competition": {
        "name": "Klasa B (Stalowa Wola II)"
      },
      "homeTeam": {
        "name": "San Rozwadów (Stalowa Wola)",
        "crest": null
      },
      "awayTeam": {
        "name": "Huragan Zdziechowice",
        "crest": null
      },
      "date": {
        "date": "2026-09-13",
        "dateTime": "2026-09-13T17:00:00.000Z"
      },
      "id": "24e42c63dad5b875029fa097bc33e47c"
    },
    {
      "competition": {
        "name": "Klasa B (Stalowa Wola II)"
      },
      "homeTeam": {
        "name": "WKS Kurzyna",
        "crest": null
      },
      "awayTeam": {
        "name": "Ceramika Harasiuki",
        "crest": null
      },
      "date": {
        "date": "2026-09-14",
        "dateTime": "2026-09-14T11:00:00.000Z"
      },
      "id": "2b83a600f4ad74e8daff07a7333cd09d"
    },
    {
      "competition": {
        "name": "Klasa B (Stalowa Wola II)"
      },
      "homeTeam": {
        "name": "Orzeł Glinianka",
        "crest": null
      },
      "awayTeam": {
        "name": "LZS Turbia",
        "crest": null
      },
      "date": {
        "date": "2026-09-14",
        "dateTime": "2026-09-14T13:00:00.000Z"
      },
      "id": "6783d7ac5ee240b372f92e2c9fa25695"
    },
    {
      "competition": {
        "name": "Klasa B (Stalowa Wola II)"
      },
      "homeTeam": {
        "name": "LZS Przędzel",
        "crest": null
      },
      "awayTeam": {
        "name": "Herosi Krzaki-Słomiana",
        "crest": null
      },
      "date": {
        "date": "2026-09-14",
        "dateTime": "2026-09-14T15:00:00.000Z"
      },
      "id": "d326245ded6cee6ac312304710d0b6cd"
    },
    {
      "competition": {
        "name": "Klasa B (Stalowa Wola II)"
      },
      "homeTeam": {
        "name": "Huragan Zdziechowice",
        "crest": null
      },
      "awayTeam": {
        "name": "Jutrzenka Kopki",
        "crest": null
      },
      "date": {
        "date": "2026-09-20",
        "dateTime": "2026-09-20T17:00:00.000Z"
      },
      "id": "00d8cce09a73b483644a8ea5501a9051"
    },
    {
      "competition": {
        "name": "Klasa B (Stalowa Wola II)"
      },
      "homeTeam": {
        "name": "Ceramika Harasiuki",
        "crest": null
      },
      "awayTeam": {
        "name": "Sanna Zaklików",
        "crest": null
      },
      "date": {
        "date": "2026-09-21",
        "dateTime": "2026-09-21T11:00:00.000Z"
      },
      "id": "400b8121e882fe6c16c21fa71547289a"
    },
    {
      "competition": {
        "name": "Klasa B (Stalowa Wola II)"
      },
      "homeTeam": {
        "name": "Orzeł Rudnik nad Sanem",
        "crest": null
      },
      "awayTeam": {
        "name": "WKS Kurzyna",
        "crest": null
      },
      "date": {
        "date": "2026-09-21",
        "dateTime": "2026-09-21T12:00:00.000Z"
      },
      "id": "1994250de0197e94f0ec78061a96d02e"
    },
    {
      "competition": {
        "name": "Klasa B (Stalowa Wola II)"
      },
      "homeTeam": {
        "name": "LZS Rzeczyca Długa",
        "crest": null
      },
      "awayTeam": {
        "name": "Czarni II Lipa",
        "crest": null
      },
      "date": {
        "date": "2026-09-21",
        "dateTime": "2026-09-21T13:00:00.000Z"
      },
      "id": "1e3b24016bab608dc312f55d1e6368be"
    },
    {
      "competition": {
        "name": "Klasa B (Stalowa Wola II)"
      },
      "homeTeam": {
        "name": "Rotunda Krzeszów",
        "crest": null
      },
      "awayTeam": {
        "name": "Orzeł Glinianka",
        "crest": null
      },
      "date": {
        "date": "2026-09-21",
        "dateTime": "2026-09-21T13:00:00.000Z"
      },
      "id": "17e02fae059a503b56ed80443bfdb18a"
    },
    {
      "competition": {
        "name": "Klasa B (Stalowa Wola II)"
      },
      "homeTeam": {
        "name": "LZS Turbia",
        "crest": null
      },
      "awayTeam": {
        "name": "LZS Przędzel",
        "crest": null
      },
      "date": {
        "date": "2026-09-21",
        "dateTime": "2026-09-21T15:00:00.000Z"
      },
      "id": "bc50f1756c9a4228443c9508c55ce26a"
    },
    {
      "competition": {
        "name": "Klasa B (Stalowa Wola II)"
      },
      "homeTeam": {
        "name": "Herosi Krzaki-Słomiana",
        "crest": null
      },
      "awayTeam": {
        "name": "San Rozwadów (Stalowa Wola)",
        "crest": null
      },
      "date": {
        "date": "2026-09-21",
        "dateTime": "2026-09-21T16:30:00.000Z"
      },
      "id": "53a8e308e62cd82eacc67fb3c3c2ea6a"
    },
    {
      "competition": {
        "name": "Klasa B (Stalowa Wola II)"
      },
      "homeTeam": {
        "name": "Czarni II Lipa",
        "crest": null
      },
      "awayTeam": {
        "name": "WKS Kurzyna",
        "crest": null
      },
      "date": {
        "date": "2026-09-27",
        "dateTime": "2026-09-27T15:00:00.000Z"
      },
      "id": "c13e1a67babc893ff87779200d49bd6e"
    },
    {
      "competition": {
        "name": "Klasa B (Stalowa Wola II)"
      },
      "homeTeam": {
        "name": "Sanna Zaklików",
        "crest": null
      },
      "awayTeam": {
        "name": "Orzeł Rudnik nad Sanem",
        "crest": null
      },
      "date": {
        "date": "2026-09-27",
        "dateTime": "2026-09-27T16:00:00.000Z"
      },
      "id": "1c4a8511bf0f3a506bc878d977c95eea"
    },
    {
      "competition": {
        "name": "Klasa B (Stalowa Wola II)"
      },
      "homeTeam": {
        "name": "Orzeł Glinianka",
        "crest": null
      },
      "awayTeam": {
        "name": "Ceramika Harasiuki",
        "crest": null
      },
      "date": {
        "date": "2026-09-28",
        "dateTime": "2026-09-28T13:00:00.000Z"
      },
      "id": "7eb6afa723362e5099f7659e2da6e433"
    },
    {
      "competition": {
        "name": "Klasa B (Stalowa Wola II)"
      },
      "homeTeam": {
        "name": "LZS Przędzel",
        "crest": null
      },
      "awayTeam": {
        "name": "Rotunda Krzeszów",
        "crest": null
      },
      "date": {
        "date": "2026-09-28",
        "dateTime": "2026-09-28T13:00:00.000Z"
      },
      "id": "74b1b3e06cd3e8977edf5a57e142681d"
    },
    {
      "competition": {
        "name": "Klasa B (Stalowa Wola II)"
      },
      "homeTeam": {
        "name": "San Rozwadów (Stalowa Wola)",
        "crest": null
      },
      "awayTeam": {
        "name": "LZS Turbia",
        "crest": null
      },
      "date": {
        "date": "2026-09-28",
        "dateTime": "2026-09-28T13:00:00.000Z"
      },
      "id": "b7c86bc4bd2ffd24d8921b319c14b58a"
    },
    {
      "competition": {
        "name": "Klasa B (Stalowa Wola II)"
      },
      "homeTeam": {
        "name": "LZS Rzeczyca Długa",
        "crest": null
      },
      "awayTeam": {
        "name": "Huragan Zdziechowice",
        "crest": null
      },
      "date": {
        "date": "2026-09-28",
        "dateTime": "2026-09-28T13:00:00.000Z"
      },
      "id": "dfa843d40ea42521dd8698530175b61f"
    },
    {
      "competition": {
        "name": "Klasa B (Stalowa Wola II)"
      },
      "homeTeam": {
        "name": "Jutrzenka Kopki",
        "crest": null
      },
      "awayTeam": {
        "name": "Herosi Krzaki-Słomiana",
        "crest": null
      },
      "date": {
        "date": "2026-09-28",
        "dateTime": "2026-09-28T16:00:00.000Z"
      },
      "id": "12349c32db4e54e6051e757d79694178"
    },
    {
      "competition": {
        "name": "Klasa B (Stalowa Wola II)"
      },
      "homeTeam": {
        "name": "Orzeł Rudnik nad Sanem",
        "crest": null
      },
      "awayTeam": {
        "name": "Orzeł Glinianka",
        "crest": null
      },
      "date": {
        "date": "2026-10-04",
        "dateTime": "2026-10-04T15:30:00.000Z"
      },
      "id": "2ad16fba0de732266f36f9f8c5f860c0"
    },
    {
      "competition": {
        "name": "Klasa B (Stalowa Wola II)"
      },
      "homeTeam": {
        "name": "Huragan Zdziechowice",
        "crest": null
      },
      "awayTeam": {
        "name": "Czarni II Lipa",
        "crest": null
      },
      "date": {
        "date": "2026-10-05",
        "dateTime": "2026-10-05T12:00:00.000Z"
      },
      "id": "1ce1e245cff8f37a2ef2a0b55456cbf4"
    },
    {
      "competition": {
        "name": "Klasa B (Stalowa Wola II)"
      },
      "homeTeam": {
        "name": "Ceramika Harasiuki",
        "crest": null
      },
      "awayTeam": {
        "name": "LZS Przędzel",
        "crest": null
      },
      "date": {
        "date": "2026-10-05",
        "dateTime": "2026-10-05T12:00:00.000Z"
      },
      "id": "f675373c86cf47e3999dcef3421e266b"
    },
    {
      "competition": {
        "name": "Klasa B (Stalowa Wola II)"
      },
      "homeTeam": {
        "name": "WKS Kurzyna",
        "crest": null
      },
      "awayTeam": {
        "name": "Sanna Zaklików",
        "crest": null
      },
      "date": {
        "date": "2026-10-05",
        "dateTime": "2026-10-05T12:00:00.000Z"
      },
      "id": "9825aa6d8e952730be876f5120a634b2"
    },
    {
      "competition": {
        "name": "Klasa B (Stalowa Wola II)"
      },
      "homeTeam": {
        "name": "Herosi Krzaki-Słomiana",
        "crest": null
      },
      "awayTeam": {
        "name": "LZS Rzeczyca Długa",
        "crest": null
      },
      "date": {
        "date": "2026-10-05",
        "dateTime": "2026-10-05T12:30:00.000Z"
      },
      "id": "a04ec4df901b96405ba879060180e361"
    },
    {
      "competition": {
        "name": "Klasa B (Stalowa Wola II)"
      },
      "homeTeam": {
        "name": "LZS Turbia",
        "crest": null
      },
      "awayTeam": {
        "name": "Jutrzenka Kopki",
        "crest": null
      },
      "date": {
        "date": "2026-10-05",
        "dateTime": "2026-10-05T15:00:00.000Z"
      },
      "id": "6286a33e88d2d0695a494647e44501b7"
    },
    {
      "competition": {
        "name": "Klasa B (Stalowa Wola II)"
      },
      "homeTeam": {
        "name": "Rotunda Krzeszów",
        "crest": null
      },
      "awayTeam": {
        "name": "San Rozwadów (Stalowa Wola)",
        "crest": null
      },
      "date": {
        "date": "2026-10-05",
        "dateTime": "2026-10-05T16:00:00.000Z"
      },
      "id": "f1a11c22cd964f4ef720dde133035592"
    },
    {
      "competition": {
        "name": "Klasa B (Stalowa Wola II)"
      },
      "homeTeam": {
        "name": "Czarni II Lipa",
        "crest": null
      },
      "awayTeam": {
        "name": "Sanna Zaklików",
        "crest": null
      },
      "date": {
        "date": "2026-10-10",
        "dateTime": "2026-10-10T19:00:00.000Z"
      },
      "id": "c55cf7d4bb33e57eb4317b1c483dfb23"
    },
    {
      "competition": {
        "name": "Klasa B (Stalowa Wola II)"
      },
      "homeTeam": {
        "name": "LZS Rzeczyca Długa",
        "crest": null
      },
      "awayTeam": {
        "name": "LZS Turbia",
        "crest": null
      },
      "date": {
        "date": "2026-10-11",
        "dateTime": "2026-10-11T15:00:00.000Z"
      },
      "id": "bca9dcf6c416c79f2a10ce2b72b56094"
    },
    {
      "competition": {
        "name": "Klasa B (Stalowa Wola II)"
      },
      "homeTeam": {
        "name": "Orzeł Glinianka",
        "crest": null
      },
      "awayTeam": {
        "name": "WKS Kurzyna",
        "crest": null
      },
      "date": {
        "date": "2026-10-12",
        "dateTime": "2026-10-12T12:00:00.000Z"
      },
      "id": "13043430aee62f1e3f5f236ab4f668a0"
    },
    {
      "competition": {
        "name": "Klasa B (Stalowa Wola II)"
      },
      "homeTeam": {
        "name": "LZS Przędzel",
        "crest": null
      },
      "awayTeam": {
        "name": "Orzeł Rudnik nad Sanem",
        "crest": null
      },
      "date": {
        "date": "2026-10-12",
        "dateTime": "2026-10-12T12:00:00.000Z"
      },
      "id": "f63fec4e876de2c1c2cdc57b73b43e6d"
    },
    {
      "competition": {
        "name": "Klasa B (Stalowa Wola II)"
      },
      "homeTeam": {
        "name": "San Rozwadów (Stalowa Wola)",
        "crest": null
      },
      "awayTeam": {
        "name": "Ceramika Harasiuki",
        "crest": null
      },
      "date": {
        "date": "2026-10-12",
        "dateTime": "2026-10-12T12:00:00.000Z"
      },
      "id": "c7a403b69c2256bf1d9a57219cb20c04"
    },
    {
      "competition": {
        "name": "Klasa B (Stalowa Wola II)"
      },
      "homeTeam": {
        "name": "Huragan Zdziechowice",
        "crest": null
      },
      "awayTeam": {
        "name": "Herosi Krzaki-Słomiana",
        "crest": null
      },
      "date": {
        "date": "2026-10-12",
        "dateTime": "2026-10-12T12:00:00.000Z"
      },
      "id": "a15aa437e921cf44feeefbd5cd121bc3"
    },
    {
      "competition": {
        "name": "Klasa B (Stalowa Wola II)"
      },
      "homeTeam": {
        "name": "Jutrzenka Kopki",
        "crest": null
      },
      "awayTeam": {
        "name": "Rotunda Krzeszów",
        "crest": null
      },
      "date": {
        "date": "2026-10-12",
        "dateTime": "2026-10-12T15:30:00.000Z"
      },
      "id": "82320e164fc15ac7b4952fd33252464a"
    },
    {
      "competition": {
        "name": "Klasa B (Stalowa Wola II)"
      },
      "homeTeam": {
        "name": "Orzeł Rudnik nad Sanem",
        "crest": null
      },
      "awayTeam": {
        "name": "San Rozwadów (Stalowa Wola)",
        "crest": null
      },
      "date": {
        "date": "2026-10-18",
        "dateTime": "2026-10-18T14:30:00.000Z"
      },
      "id": "a7f4d8e3e2c8ff82c4924f5b2f5ece31"
    },
    {
      "competition": {
        "name": "Klasa B (Stalowa Wola II)"
      },
      "homeTeam": {
        "name": "Rotunda Krzeszów",
        "crest": null
      },
      "awayTeam": {
        "name": "LZS Rzeczyca Długa",
        "crest": null
      },
      "date": {
        "date": "2026-10-19",
        "dateTime": "2026-10-19T11:00:00.000Z"
      },
      "id": "036fa40ee57c858c6d52850f3e398563"
    },
    {
      "competition": {
        "name": "Klasa B (Stalowa Wola II)"
      },
      "homeTeam": {
        "name": "Herosi Krzaki-Słomiana",
        "crest": null
      },
      "awayTeam": {
        "name": "Czarni II Lipa",
        "crest": null
      },
      "date": {
        "date": "2026-10-19",
        "dateTime": "2026-10-19T12:00:00.000Z"
      },
      "id": "d09661d1d3c3ae5f805fd4ee7fbbac12"
    },
    {
      "competition": {
        "name": "Klasa B (Stalowa Wola II)"
      },
      "homeTeam": {
        "name": "LZS Turbia",
        "crest": null
      },
      "awayTeam": {
        "name": "Huragan Zdziechowice",
        "crest": null
      },
      "date": {
        "date": "2026-10-19",
        "dateTime": "2026-10-19T12:00:00.000Z"
      },
      "id": "2d2dbcaf1e049710c9ae9cb7ad04c99d"
    },
    {
      "competition": {
        "name": "Klasa B (Stalowa Wola II)"
      },
      "homeTeam": {
        "name": "Ceramika Harasiuki",
        "crest": null
      },
      "awayTeam": {
        "name": "Jutrzenka Kopki",
        "crest": null
      },
      "date": {
        "date": "2026-10-19",
        "dateTime": "2026-10-19T12:00:00.000Z"
      },
      "id": "754244511edeb3eafdbd038aa6f74a04"
    },
    {
      "competition": {
        "name": "Klasa B (Stalowa Wola II)"
      },
      "homeTeam": {
        "name": "WKS Kurzyna",
        "crest": null
      },
      "awayTeam": {
        "name": "LZS Przędzel",
        "crest": null
      },
      "date": {
        "date": "2026-10-19",
        "dateTime": "2026-10-19T12:00:00.000Z"
      },
      "id": "08360e189dbcac24d5b2c03ee702368c"
    },
    {
      "competition": {
        "name": "Klasa B (Stalowa Wola II)"
      },
      "homeTeam": {
        "name": "Sanna Zaklików",
        "crest": null
      },
      "awayTeam": {
        "name": "Orzeł Glinianka",
        "crest": null
      },
      "date": {
        "date": "2026-10-19",
        "dateTime": "2026-10-19T15:30:00.000Z"
      },
      "id": "0383f87ba6f4d659f982cfa9644578ad"
    },
    {
      "competition": {
        "name": "Klasa B (Stalowa Wola II)"
      },
      "homeTeam": {
        "name": "Czarni II Lipa",
        "crest": null
      },
      "awayTeam": {
        "name": "Orzeł Glinianka",
        "crest": null
      },
      "date": {
        "date": "2026-10-25",
        "dateTime": "2026-10-25T14:00:00.000Z"
      },
      "id": "9be49f0185276c68c311079f77f9f3eb"
    },
    {
      "competition": {
        "name": "Klasa B (Stalowa Wola II)"
      },
      "homeTeam": {
        "name": "Huragan Zdziechowice",
        "crest": null
      },
      "awayTeam": {
        "name": "Rotunda Krzeszów",
        "crest": null
      },
      "date": {
        "date": "2026-10-25",
        "dateTime": "2026-10-25T15:00:00.000Z"
      },
      "id": "8d73b22087c2c5abd2b48a7fcb6f8c28"
    },
    {
      "competition": {
        "name": "Klasa B (Stalowa Wola II)"
      },
      "homeTeam": {
        "name": "Herosi Krzaki-Słomiana",
        "crest": null
      },
      "awayTeam": {
        "name": "LZS Turbia",
        "crest": null
      },
      "date": {
        "date": "2026-10-26",
        "dateTime": "2026-10-26T10:00:00.000Z"
      },
      "id": "fa34b1d09e9925daec6830b8ccee98fc"
    },
    {
      "competition": {
        "name": "Klasa B (Stalowa Wola II)"
      },
      "homeTeam": {
        "name": "San Rozwadów (Stalowa Wola)",
        "crest": null
      },
      "awayTeam": {
        "name": "WKS Kurzyna",
        "crest": null
      },
      "date": {
        "date": "2026-10-26",
        "dateTime": "2026-10-26T12:00:00.000Z"
      },
      "id": "52e70cb8720f7f5a2dd09767ee402687"
    },
    {
      "competition": {
        "name": "Klasa B (Stalowa Wola II)"
      },
      "homeTeam": {
        "name": "LZS Rzeczyca Długa",
        "crest": null
      },
      "awayTeam": {
        "name": "Ceramika Harasiuki",
        "crest": null
      },
      "date": {
        "date": "2026-10-26",
        "dateTime": "2026-10-26T12:00:00.000Z"
      },
      "id": "883f884e9771ef684884160f61be0874"
    },
    {
      "competition": {
        "name": "Klasa B (Stalowa Wola II)"
      },
      "homeTeam": {
        "name": "LZS Przędzel",
        "crest": null
      },
      "awayTeam": {
        "name": "Sanna Zaklików",
        "crest": null
      },
      "date": {
        "date": "2026-10-26",
        "dateTime": "2026-10-26T14:00:00.000Z"
      },
      "id": "8d8e7fc82c5b67ba6d3912f48bea855e"
    },
    {
      "competition": {
        "name": "Klasa B (Stalowa Wola II)"
      },
      "homeTeam": {
        "name": "Jutrzenka Kopki",
        "crest": null
      },
      "awayTeam": {
        "name": "Orzeł Rudnik nad Sanem",
        "crest": null
      },
      "date": {
        "date": "2026-10-26",
        "dateTime": "2026-10-26T14:00:00.000Z"
      },
      "id": "eb7ab2353bba96b216e5aaa662687480"
    },
    {
      "competition": {
        "name": "Klasa B (Stalowa Wola II)"
      },
      "homeTeam": {
        "name": "LZS Turbia",
        "crest": null
      },
      "awayTeam": {
        "name": "Czarni II Lipa",
        "crest": null
      },
      "date": {
        "date": "2026-11-02",
        "dateTime": "2026-11-02T11:00:00.000Z"
      },
      "id": "217c09abad0c3612c18aea82a797f27e"
    },
    {
      "competition": {
        "name": "Klasa B (Stalowa Wola II)"
      },
      "homeTeam": {
        "name": "Rotunda Krzeszów",
        "crest": null
      },
      "awayTeam": {
        "name": "Herosi Krzaki-Słomiana",
        "crest": null
      },
      "date": {
        "date": "2026-11-02",
        "dateTime": "2026-11-02T11:00:00.000Z"
      },
      "id": "2bd7327b060031e09ec22b0ec7b034fa"
    },
    {
      "competition": {
        "name": "Klasa B (Stalowa Wola II)"
      },
      "homeTeam": {
        "name": "Ceramika Harasiuki",
        "crest": null
      },
      "awayTeam": {
        "name": "Huragan Zdziechowice",
        "crest": null
      },
      "date": {
        "date": "2026-11-02",
        "dateTime": "2026-11-02T11:00:00.000Z"
      },
      "id": "85b872a84b987c5b22fa01d536c099a2"
    },
    {
      "competition": {
        "name": "Klasa B (Stalowa Wola II)"
      },
      "homeTeam": {
        "name": "WKS Kurzyna",
        "crest": null
      },
      "awayTeam": {
        "name": "Jutrzenka Kopki",
        "crest": null
      },
      "date": {
        "date": "2026-11-02",
        "dateTime": "2026-11-02T11:00:00.000Z"
      },
      "id": "6d1dbba10af104662d87bd16e2c188b8"
    },
    {
      "competition": {
        "name": "Klasa B (Stalowa Wola II)"
      },
      "homeTeam": {
        "name": "Sanna Zaklików",
        "crest": null
      },
      "awayTeam": {
        "name": "San Rozwadów (Stalowa Wola)",
        "crest": null
      },
      "date": {
        "date": "2026-11-02",
        "dateTime": "2026-11-02T11:00:00.000Z"
      },
      "id": "c7c1e7f0e01c7476748a7505d40a0755"
    },
    {
      "competition": {
        "name": "Klasa B (Stalowa Wola II)"
      },
      "homeTeam": {
        "name": "Orzeł Rudnik nad Sanem",
        "crest": null
      },
      "awayTeam": {
        "name": "LZS Rzeczyca Długa",
        "crest": null
      },
      "date": {
        "date": "2026-11-02",
        "dateTime": "2026-11-02T12:00:00.000Z"
      },
      "id": "97638f2a00498d2fc3f31f3ab431b541"
    },
    {
      "competition": {
        "name": "Klasa B (Stalowa Wola II)"
      },
      "homeTeam": {
        "name": "Orzeł Glinianka",
        "crest": null
      },
      "awayTeam": {
        "name": "LZS Przędzel",
        "crest": null
      },
      "date": {
        "date": "2026-11-02",
        "dateTime": "2026-11-02T13:00:00.000Z"
      },
      "id": "742e5532167be7e1aa898fc51e929e96"
    }
  ]
}